robovat/__init__.py
robovat/envs/__init__.py
robovat/envs/arm_env.py
robovat/envs/robot_env.py
robovat/envs/grasp/__init__.py
robovat/envs/grasp/grasp_2d.py
robovat/envs/grasp/grasp_4dof_env.py
robovat/envs/grasp/image_grasp_sampler.py
robovat/envs/grasp/visualize.py
robovat/envs/push/__init__.py
robovat/envs/push/heuristic_push_sampler.py
robovat/envs/push/layouts.py
robovat/envs/push/push_env.py
robovat/io/__init__.py
robovat/io/episode_generation.py
robovat/io/hdf5_utils.py
robovat/io/pickle_utils.py
robovat/math/__init__.py
robovat/math/euler.py
robovat/math/orientation.py
robovat/math/point.py
robovat/math/pose.py
robovat/math/quaternion.py
robovat/observations/__init__.py
robovat/observations/action_obs.py
robovat/observations/attribute_obs.py
robovat/observations/camera_obs.py
robovat/observations/observation.py
robovat/observations/pose_obs.py
robovat/perception/__init__.py
robovat/perception/depth_utils.py
robovat/perception/image_utils.py
robovat/perception/point_cloud_utils.py
robovat/perception/camera/__init__.py
robovat/perception/camera/camera.py
robovat/perception/camera/kinect2.py
robovat/policies/__init__.py
robovat/policies/grasp_policy.py
robovat/policies/policy.py
robovat/policies/push_policy.py
robovat/policies/random_policy.py
robovat/reward_fns/__init__.py
robovat/reward_fns/grasp_reward.py
robovat/reward_fns/push_reward.py
robovat/reward_fns/reward_fn.py
robovat/robots/__init__.py
robovat/robots/robot.py
robovat/robots/robot_command.py
robovat/robots/sawyer/__init__.py
robovat/robots/sawyer/sawyer.py
robovat/robots/sawyer/sawyer_real.py
robovat/robots/sawyer/sawyer_sim.py
robovat/simulation/__init__.py
robovat/simulation/base.py
robovat/simulation/body.py
robovat/simulation/constraint.py
robovat/simulation/controllable_body.py
robovat/simulation/controllable_constraint.py
robovat/simulation/entity.py
robovat/simulation/joint.py
robovat/simulation/link.py
robovat/simulation/simulator.py
robovat/simulation/camera/__init__.py
robovat-0.1.0.dist-info/LICENSE
robovat-0.1.0.dist-info/METADATA
robovat-0.1.0.dist-info/WHEEL
robovat-0.1.0.dist-info/top_level.txt
robovat-0.1.0.dist-info/RECORD
