Metadata-Version: 2.1
Name: robovat
Version: 0.1.0
Summary: RoboVat: A unified toolkit for simulated and real-world robotic task environments.
Home-page: https://github.com/StanfordVL/robovat
Author: Kuan Fang
Author-email: kuanfang@ai.stanford.edu
License: MIT
Platform: UNKNOWN
Requires-Dist: easydict (==1.9)
Requires-Dist: future (==0.17.1)
Requires-Dist: gym (==0.14.0)
Requires-Dist: h5py (==2.9.0)
Requires-Dist: matplotlib (==2.2.4)
Requires-Dist: numpy (==1.16.5)
Requires-Dist: opencv-python (==4.1.0.25)
Requires-Dist: Pillow (==6.1.0)
Requires-Dist: python-pcl
Requires-Dist: PyYAML (==5.1.2)
Requires-Dist: scikit-learn (==0.20.4)
Requires-Dist: scipy (==1.2.2)
Requires-Dist: six (==1.11.0)
Requires-Dist: sklearn (==0.0)
Requires-Dist: pybullet (==2.6.5)
